makelint/__init__.py
makelint/__main__.py
makelint/configuration.py
makelint/get_dependencies.py
makelint-0.1.0.dist-info/LICENSE
makelint-0.1.0.dist-info/METADATA
makelint-0.1.0.dist-info/WHEEL
makelint-0.1.0.dist-info/entry_points.txt
makelint-0.1.0.dist-info/top_level.txt
makelint-0.1.0.dist-info/RECORD
