Metadata-Version: 2.1
Name: makelint
Version: 0.1.0
Summary: A highly-compatible "build" system for linting python files.
Home-page: https://github.com/cheshirekow/makelint
Author: Josh Bialkowski
Author-email: josh.bialkowski@gmail.com
License: UNKNOWN
Download-URL: https://github.com/cheshirekow/makelint/archive/0.1.0.tar.gz
Keywords: lint,static-analysis,code-checker
Platform: UNKNOWN
